[
  {
    "name": "Rosas rojas",
    "url": "https://monparnasse.es/cdn/shop/files/39A1290_d6f09b23-5f88-472f-8af1-2825cf840bcc.jpg?v=1707469399&width=1500"
  },
  {
    "name": "Rosas blancas",
    "url": "https://monparnasse.es/cdn/shop/files/IMG_1812.jpg?v=1706721019&width=1500"
  },
  {
    "name": "Rosas rosas",
    "url": "https://monparnasse.es/cdn/shop/files/IMG_1837.jpg?v=1706721275&width=1500"
  },
  {
    "name": "Tulipanes rojos",
    "url": "https://monparnasse.es/cdn/shop/files/IMG_1684a.jpg?v=1706716854&width=1500"
  },
  {
    "name": "Tulipanes blancos",
    "url": "https://monparnasse.es/cdn/shop/files/IMG_1709.jpg?v=1706720140&width=1500"
  },
  {
    "name": "Tulipanes rosas",
    "url": "https://monparnasse.es/cdn/shop/files/IMG_1711.jpg?v=1706719864&width=1500"
  },

  {
    "name": "Lilium rosa",
    "url": "https://monparnasse.es/cdn/shop/files/IMG_1863.jpg?v=1706782443&width=1500"
  },
  {
    "name": "Orquídea Phalaenopsis",
    "url": "https://monparnasse.es/cdn/shop/files/39A5117.jpg?v=1697452519&width=1500"
  },
  {
    "name": "Orquídea Dendrobium",
    "url": "https://monparnasse.es/cdn/shop/files/39A3229.jpg?v=1697449632&width=1500"
  },
  {
    "name": "Anthurium",
    "url": "https://monparnasse.es/cdn/shop/files/39A3386_1_405e0eb6-fc83-4ea3-bf98-6b203e70e390.jpg?v=1697039491&width=1500"
  },
  {
    "name": "Zamioculca",
    "url": "https://monparnasse.es/cdn/shop/files/39A5041.jpg?v=1697453542&width=1500"
  },
  {
    "name": "Spathiphyllum",
    "url": "https://monparnasse.es/cdn/shop/files/39A5013.jpg?v=1697452976&width=1500"
  },
  {
    "name": "Calathea",
    "url": "https://monparnasse.es/cdn/shop/files/39A9271.jpg?v=1697455561&width=1500"
  },
  {
    "name": "Beucarnea",
    "url": "https://monparnasse.es/cdn/shop/files/39A9267_872ebf60-34da-4e96-ba25-51c4ca103f04.jpg?v=1697453287&width=1500"
  },
  {
    "name": "Bromelia",
    "url": "https://monparnasse.es/cdn/shop/files/39A3272.jpg?v=1697448695&width=1500"
  },
  {
    "name": "Monstera",
    "url": "https://monparnasse.es/cdn/shop/files/39A3492.jpg?v=1697452245&width=1500"
  }
]
